mlperf_logging/__init__.py
mlperf_logging/benchmark_meta.py
mlperf_logging/compliance_checker/__init__.py
mlperf_logging/compliance_checker/__main__.py
mlperf_logging/compliance_checker/mlp_compliance.py
mlperf_logging/compliance_checker/hpc_1.0.0/closed_common.yaml
mlperf_logging/compliance_checker/hpc_1.0.0/closed_cosmoflow.yaml
mlperf_logging/compliance_checker/hpc_1.0.0/closed_deepcam.yaml
mlperf_logging/compliance_checker/hpc_1.0.0/closed_deepcam_cosine_annealing.yaml
mlperf_logging/compliance_checker/hpc_1.0.0/closed_deepcam_lamb.yaml
mlperf_logging/compliance_checker/hpc_1.0.0/closed_deepcam_multistep.yaml
mlperf_logging/compliance_checker/hpc_1.0.0/closed_oc20.yaml
mlperf_logging/compliance_checker/hpc_1.0.0/common.yaml
mlperf_logging/compliance_checker/hpc_1.0.0/open_common.yaml
mlperf_logging/compliance_checker/hpc_1.0.0/open_cosmoflow.yaml
mlperf_logging/compliance_checker/hpc_1.0.0/open_deepcam.yaml
mlperf_logging/compliance_checker/hpc_1.0.0/open_oc20.yaml
mlperf_logging/compliance_checker/hpc_2.0.0/closed_common.yaml
mlperf_logging/compliance_checker/hpc_2.0.0/closed_cosmoflow.yaml
mlperf_logging/compliance_checker/hpc_2.0.0/closed_deepcam.yaml
mlperf_logging/compliance_checker/hpc_2.0.0/closed_deepcam_cosine_annealing.yaml
mlperf_logging/compliance_checker/hpc_2.0.0/closed_deepcam_lamb.yaml
mlperf_logging/compliance_checker/hpc_2.0.0/closed_deepcam_multistep.yaml
mlperf_logging/compliance_checker/hpc_2.0.0/closed_oc20.yaml
mlperf_logging/compliance_checker/hpc_2.0.0/common.yaml
mlperf_logging/compliance_checker/hpc_2.0.0/open_common.yaml
mlperf_logging/compliance_checker/hpc_2.0.0/open_cosmoflow.yaml
mlperf_logging/compliance_checker/hpc_2.0.0/open_deepcam.yaml
mlperf_logging/compliance_checker/hpc_2.0.0/open_oc20.yaml
mlperf_logging/compliance_checker/hpc_3.0.0/closed_common.yaml
mlperf_logging/compliance_checker/hpc_3.0.0/closed_cosmoflow.yaml
mlperf_logging/compliance_checker/hpc_3.0.0/closed_deepcam.yaml
mlperf_logging-4.1.38.dist-info/licenses/LICENSE.md
mlperf_logging-4.1.38.dist-info/METADATA
mlperf_logging-4.1.38.dist-info/WHEEL
mlperf_logging-4.1.38.dist-info/top_level.txt
mlperf_logging-4.1.38.dist-info/RECORD
