Metadata-Version: 2.4
Name: mlperf-logging
Version: 4.1.38
Summary: MLPerf compliance tools.
Home-page: https://github.com/mlperf/logging
Author: MLPerf.org
Author-email: mlperf@googlegroups.com
License: Apache 2.0
Classifier: Programming Language :: Python :: 2
Classifier: Programming Language :: Python :: 3
Classifier: License :: OSI Approved :: Apache Software License
Classifier: Operating System :: OS Independent
License-File: LICENSE.md
Requires-Dist: pandas>=1.0
Requires-Dist: pyyaml>=5.4.1
Requires-Dist: numpy>=1.17.3
Requires-Dist: scipy>=1.4.1
Dynamic: author
Dynamic: author-email
Dynamic: classifier
Dynamic: description
Dynamic: description-content-type
Dynamic: home-page
Dynamic: license
Dynamic: license-file
Dynamic: requires-dist
Dynamic: summary
